xmippLib.so
pyxmipp3-0.1.0.dist-info/METADATA
pyxmipp3-0.1.0.dist-info/WHEEL
pyxmipp3-0.1.0.dist-info/RECORD
pyxmipp3-0.1.0.dist-info/licenses/LICENSE
