Metadata-Version: 2.4
Name: pyxmipp3
Version: 0.1.0
Summary: Minimal version of xmipp3 package with Python bindings
Author-Email: Oier Lauzirika Zarrabeitia <oierlauzi@bizkaia.eu>
License-Expression: GPL-3.0-only
Classifier: Topic :: Scientific/Engineering :: Image Processing
Classifier: Intended Audience :: Science/Research
Classifier: Intended Audience :: Developers
Classifier: Operating System :: OS Independent
Classifier: Programming Language :: Python
Classifier: Programming Language :: Python :: 3
Classifier: Programming Language :: Python :: 3 :: Only
Classifier: Programming Language :: Python :: 3.7
Classifier: Programming Language :: Python :: 3.8
Classifier: Programming Language :: Python :: 3.9
Classifier: Programming Language :: Python :: 3.10
Classifier: Programming Language :: Python :: 3.11
Classifier: Programming Language :: Python :: 3.12
Project-URL: Homepage, https://github.com/oierlauzi/pyxmipp3
Project-URL: Issues, https://github.com/oierlauzi/pyxmipp3/issues
Requires-Python: >=3.7
Requires-Dist: numpy==1.*
